deploy_remote/__init__.py
deploy_remote/__main__.py
deploy_remote/__version__.py
deploy_remote/deploy_linux_amd64
deploy_remote/deploy_macos_amd64
deploy_remote/deploy_macos_arm64
deploy_remote/deploy_windows_amd64.exe
deploy_remote/main.py
deploy_remote-0.0.17.dist-info/licenses/LICENSE
deploy_remote-0.0.17.dist-info/METADATA
deploy_remote-0.0.17.dist-info/WHEEL
deploy_remote-0.0.17.dist-info/entry_points.txt
deploy_remote-0.0.17.dist-info/top_level.txt
deploy_remote-0.0.17.dist-info/RECORD
